countdowntimer_model/__init__.py
countdowntimer_model/apps.py
countdowntimer_model/constants.py
countdowntimer_model/models.py
countdowntimer_model_project/__init__.py
countdowntimer_model_project/asgi.py
countdowntimer_model_project/settings.py
countdowntimer_model_project/urls.py
countdowntimer_model_project/wsgi.py
django_countdowntimer_model-0.0.7.dist-info/LICENSE
django_countdowntimer_model-0.0.7.dist-info/METADATA
django_countdowntimer_model-0.0.7.dist-info/WHEEL
django_countdowntimer_model-0.0.7.dist-info/top_level.txt
django_countdowntimer_model-0.0.7.dist-info/RECORD
